yt_scrapper.py
YT_comments_scrapper-0.3.dist-info/LICENSE
YT_comments_scrapper-0.3.dist-info/METADATA
YT_comments_scrapper-0.3.dist-info/WHEEL
YT_comments_scrapper-0.3.dist-info/top_level.txt
YT_comments_scrapper-0.3.dist-info/RECORD
