Metadata-Version: 2.1
Name: YT-comments-scrapper
Version: 0.3
Summary: YouTube comments scrapper
Home-page: https://github.com/linda-oranya/YT_comments_scrapper
Author: Linda Oranya
Author-email: oranyalinda7@gmail.com
License: UNKNOWN
Project-URL: Bug Tracker, https://github.com/linda-oranya/YT_comments_scrapper/issues
Platform: UNKNOWN
Classifier: Programming Language :: Python :: 3
Classifier: License :: OSI Approved :: MIT License
Classifier: Operating System :: OS Independent
Requires-Python: >=3.6
